pyrr/__init__.py
pyrr/aabb.py
pyrr/aambb.py
pyrr/euler.py
pyrr/geometric_tests.py
pyrr/geometry.py
pyrr/integer.py
pyrr/line.py
pyrr/matrix33.py
pyrr/matrix44.py
pyrr/plane.py
pyrr/quaternion.py
pyrr/ray.py
pyrr/rectangle.py
pyrr/sphere.py
pyrr/trig.py
pyrr/utils.py
pyrr/vector.py
pyrr/vector3.py
pyrr/vector4.py
pyrr/version.py
pyrr/objects/__init__.py
pyrr/objects/base.py
pyrr/objects/matrix33.py
pyrr/objects/matrix44.py
pyrr/objects/quaternion.py
pyrr/objects/vector3.py
pyrr/objects/vector4.py
pyrr-0.10.2.dist-info/LICENSE
pyrr-0.10.2.dist-info/METADATA
pyrr-0.10.2.dist-info/WHEEL
pyrr-0.10.2.dist-info/top_level.txt
pyrr-0.10.2.dist-info/RECORD
