Metadata-Version: 2.1
Name: pyrr
Version: 0.10.2
Summary: 3D mathematical functions using NumPy
Home-page: https://github.com/adamlwgriffiths/Pyrr
Author: Adam Griffiths
Author-email: UNKNOWN
License: BSD
Platform: any
Classifier: Natural Language :: English
Classifier: Intended Audience :: Developers
Classifier: Operating System :: MacOS :: MacOS X
Classifier: Operating System :: Microsoft :: Windows
Classifier: Operating System :: POSIX
Classifier: Programming Language :: Python
Classifier: License :: OSI Approved :: BSD License
Classifier: Topic :: Multimedia :: Graphics
Classifier: Topic :: Scientific/Engineering :: Mathematics
Classifier: Topic :: Software Development :: Libraries
Classifier: Topic :: Software Development :: Libraries :: Python Modules
Requires-Dist: numpy
Requires-Dist: multipledispatch
